MANIFEST.in
README.md
setup.py
LeafSync/README.md
LeafSync/__init__.py
LeafSync/license.txt
LeafSync/resources.py
LeafSync/setup.cfg
LeafSync/watch.py
LeafSync.egg-info/PKG-INFO
LeafSync.egg-info/SOURCES.txt
LeafSync.egg-info/dependency_links.txt
LeafSync.egg-info/not-zip-safe
LeafSync.egg-info/top_level.txt
LeafSync/__pycache__/__init__.cpython-312.pyc
LeafSync/__pycache__/resources.cpython-312.pyc
LeafSync/__pycache__/watch.cpython-312.pyc
LeafSync/files/config.json