Metadata-Version: 2.1
Name: LeafSync
Version: 0.0.3
Author: German Espinosa
Author-email: germanespinosa@gmail.com
License: MIT
